<?xml version="1.0" encoding="UTF-8"?>
<team>
	<name>Uyghur</name>
	<goalRating>15</goalRating>
	<formation>4-3-3</formation>
	<strategy>Normal</strategy>
	<halfStats>
		<attempts>20</attempts>
		<defensiveAttempts>-3</defensiveAttempts>
		<defensiveShotsOnGoal>-2</defensiveShotsOnGoal>
	</halfStats>
	<halfStats>
		<attempts>20</attempts>
		<defensiveAttempts>-2</defensiveAttempts>
		<defensiveShotsOnGoal>-1</defensiveShotsOnGoal>
	</halfStats>
	<players>
		<player>
			<name>Hoshur</name>
			<shotRange>1-21</shotRange>
			<goal>6-10</goal>
			<injury>1-6</injury>
			<multiplier>1</multiplier>
		</player>
		<player>
			<name>Abdulwali</name>
			<shotRange>22-42</shotRange>
			<goal>6-10</goal>
			<injury>7-12</injury>
			<multiplier>0</multiplier>
		</player>
		<player>
			<name>Bozan</name>
			<shotRange>42-62</shotRange>
			<goal>6-10</goal>
			<injury>13-16</injury>
			<multiplier>0</multiplier>
		</player>
		<player>
			<name>Avutov</name>
			<shotRange>63-83</shotRange>
			<goal>6-10</goal>
			<injury>17-22</injury>
			<multiplier>0</multiplier>
		</player>
		<player>
			<name>Sabri</name>
			<shotRange>84</shotRange>
			<goal>8-10</goal>
			<injury>23-31</injury>
			<multiplier>0</multiplier>
		</player>
		<player>
			<name>Alptekin</name>
			<shotRange>85</shotRange>
			<goal>8-10</goal>
			<injury>32-37</injury>
			<multiplier>0</multiplier>
		</player>
		<player>
			<name>Navai</name>
			<shotRange>86</shotRange>
			<goal>8-10</goal>
			<injury>38-43</injury>
			<multiplier>0</multiplier>
		</player>
		<player>
			<name>Maimaiti</name>
			<shotRange>87</shotRange>
			<goal>9-10</goal>
			<injury>44-49</injury>
			<multiplier>0</multiplier>
		</player>
		<player>
			<name>Qasim</name>
			<shotRange>88</shotRange>
			<goal>9-10</goal>
			<injury>50-55</injury>
			<multiplier>1</multiplier>
		</player>
		<player>
			<name>Khoja</name>
			<shotRange>90</shotRange>
			<goal>10</goal>
			<injury>56-64</injury>
			<multiplier>0</multiplier>
		</player>
		<player>
			<name>Suleymanoglu</name>
			<shotRange>91</shotRange>
			<goal>10</goal>
			<injury>65-73</injury>
			<multiplier>0</multiplier>
		</player>
		<player>
			<name>Kilici</name>
			<shotRange>92</shotRange>
			<goal>10</goal>
			<injury>74-79</injury>
			<multiplier>0</multiplier>
		</player>
		<player>
			<name>Baykara</name>
			<shotRange>93</shotRange>
			<goal>10</goal>
			<injury>80-85</injury>
			<multiplier>0</multiplier>
		</player>
		<player>
			<name>Sener</name>
			<shotRange>94</shotRange>
			<goal>10</goal>
			<injury>86-87</injury>
			<multiplier>0</multiplier>
		</player>
		<player>
			<name>Cerci</name>
			<shotRange>95</shotRange>
			<goal>10</goal>
			<injury>88-89</injury>
			<multiplier>0</multiplier>
		</player>
		<player>
			<name>Denkel</name>
			<shotRange>96</shotRange>
			<goal>10</goal>
			<injury>90</injury>
			<multiplier>0</multiplier>
		</player>
		<player>
			<name>Ozturk</name>
			<shotRange>97</shotRange>
			<goal>10</goal>
			<injury>91</injury>
			<multiplier>0</multiplier>
		</player>
		<player>
			<name>Uzer</name>
			<shotRange>98</shotRange>
			<goal>10</goal>
			<injury>92</injury>
			<multiplier>0</multiplier>
		</player>
		<player>
			<name>Kiraz</name>
			<shotRange>99</shotRange>
			<goal>10</goal>
			<injury>93</injury>
			<multiplier>0</multiplier>
		</player>
		<player>
			<name>Sancak</name>
			<shotRange>100</shotRange>
			<goal>10</goal>
			<injury>94</injury>
			<multiplier>0</multiplier>
		</player>
		<goalie>
			<name>Samedi</name>
			<rating>0</rating>
			<injury>92-96</injury>
			<multiplier>1</multiplier>
		</goalie>
		<goalie>
			<name>Zogbo</name>
			<rating>+2</rating>
			<injury>94-98</injury>
			<multiplier>1</multiplier>
		</goalie>
		<goalie>
			<name>Yasin</name>
			<rating>+1</rating>
			<injury>x</injury>
			<multiplier>0</multiplier>
		</goalie>
	</players>
</team>